{
  "bio": {
    "birthday": "1951-10-30", 
    "gender": "M"
  }, 
  "id": {
    "aclu_id": "aclu/elections-api/congress_legislator:834", 
    "ballotpedia": "Frank Pallone", 
    "bioguide": "P000034", 
    "cspan": 6107, 
    "fec": [
      "H8NJ03073", 
      "S6NJ00263"
    ], 
    "google_entity_id": "kg:/m/0g6t5w", 
    "govtrack": 400308, 
    "house_history": 19321, 
    "icpsr": 15454, 
    "maplight": 402, 
    "opensecrets": "N00000781", 
    "thomas": "00887", 
    "votesmart": 26951, 
    "wikidata": "Q965289", 
    "wikipedia": "Frank Pallone"
  }, 
  "name": {
    "first": "Frank", 
    "last": "Pallone", 
    "middle": "J.", 
    "official_full": "Frank Pallone, Jr.", 
    "suffix": "Jr."
  }, 
  "social": {
    "facebook": "repfrankpallone", 
    "instagram": "repfrankpallone", 
    "twitter": "FrankPallone", 
    "twitter_id": 31801993, 
    "youtube": "repfrankpallone", 
    "youtube_id": "UCN0_wn9hs1LI3UKkji2PP2A"
  }, 
  "terms": [
    {
      "district": 6, 
      "end": "1989-01-03", 
      "party": "Democrat", 
      "start": "1987-01-06", 
      "state": "NJ", 
      "type": "rep"
    }, 
    {
      "district": 3, 
      "end": "1991-01-03", 
      "party": "Democrat", 
      "start": "1989-01-03", 
      "state": "NJ", 
      "type": "rep"
    }, 
    {
      "district": 3, 
      "end": "1993-01-03", 
      "party": "Democrat", 
      "start": "1991-01-03", 
      "state": "NJ", 
      "type": "rep"
    }, 
    {
      "district": 6, 
      "end": "1995-01-03", 
      "party": "Democrat", 
      "start": "1993-01-05", 
      "state": "NJ", 
      "type": "rep"
    }, 
    {
      "district": 6, 
      "end": "1997-01-03", 
      "party": "Democrat", 
      "start": "1995-01-04", 
      "state": "NJ", 
      "type": "rep"
    }, 
    {
      "district": 6, 
      "end": "1999-01-03", 
      "party": "Democrat", 
      "start": "1997-01-07", 
      "state": "NJ", 
      "type": "rep"
    }, 
    {
      "district": 6, 
      "end": "2001-01-03", 
      "party": "Democrat", 
      "start": "1999-01-06", 
      "state": "NJ", 
      "type": "rep"
    }, 
    {
      "district": 6, 
      "end": "2003-01-03", 
      "party": "Democrat", 
      "start": "2001-01-03", 
      "state": "NJ", 
      "type": "rep"
    }, 
    {
      "district": 6, 
      "end": "2005-01-03", 
      "party": "Democrat", 
      "start": "2003-01-07", 
      "state": "NJ", 
      "type": "rep", 
      "url": "http://www.house.gov/pallone"
    }, 
    {
      "district": 6, 
      "end": "2007-01-03", 
      "party": "Democrat", 
      "start": "2005-01-04", 
      "state": "NJ", 
      "type": "rep", 
      "url": "http://www.house.gov/pallone"
    }, 
    {
      "district": 6, 
      "end": "2009-01-03", 
      "party": "Democrat", 
      "start": "2007-01-04", 
      "state": "NJ", 
      "type": "rep", 
      "url": "http://www.house.gov/pallone"
    }, 
    {
      "district": 6, 
      "end": "2011-01-03", 
      "party": "Democrat", 
      "start": "2009-01-06", 
      "state": "NJ", 
      "type": "rep", 
      "url": "http://www.house.gov/pallone"
    }, 
    {
      "address": "237 Cannon HOB; Washington DC 20515-3006", 
      "contact_form": "http://www.house.gov/pallone/contact.shtml", 
      "district": 6, 
      "end": "2013-01-03", 
      "fax": "202-225-9665", 
      "office": "237 Cannon House Office Building", 
      "party": "Democrat", 
      "phone": "202-225-4671", 
      "start": "2011-01-05", 
      "state": "NJ", 
      "type": "rep", 
      "url": "http://www.house.gov/pallone"
    }, 
    {
      "address": "237 Cannon HOB; Washington DC 20515-3006", 
      "contact_form": "https://pallone.house.gov/contact-me/email-me", 
      "district": 6, 
      "end": "2015-01-03", 
      "fax": "202-225-9665", 
      "office": "237 Cannon House Office Building", 
      "party": "Democrat", 
      "phone": "202-225-4671", 
      "rss_url": "http://pallone.house.gov/rss.xml", 
      "start": "2013-01-03", 
      "state": "NJ", 
      "type": "rep", 
      "url": "http://pallone.house.gov"
    }, 
    {
      "address": "237 Cannon HOB; Washington DC 20515-3006", 
      "contact_form": "https://pallone.house.gov/contact-me/email-me", 
      "district": 6, 
      "end": "2017-01-03", 
      "fax": "202-225-9665", 
      "office": "237 Cannon House Office Building", 
      "party": "Democrat", 
      "phone": "202-225-4671", 
      "rss_url": "http://pallone.house.gov/rss.xml", 
      "start": "2015-01-06", 
      "state": "NJ", 
      "type": "rep", 
      "url": "https://pallone.house.gov"
    }, 
    {
      "address": "237 Cannon House Office Building; Washington DC 20515-3006", 
      "district": 6, 
      "end": "2019-01-03", 
      "fax": "202-225-9665", 
      "office": "237 Cannon House Office Building", 
      "party": "Democrat", 
      "phone": "202-225-4671", 
      "rss_url": "http://pallone.house.gov/rss.xml", 
      "start": "2017-01-03", 
      "state": "NJ", 
      "type": "rep", 
      "url": "https://pallone.house.gov"
    }, 
    {
      "address": "2107 Rayburn House Office Building Washington DC 20515-3006", 
      "district": 6, 
      "end": "2021-01-03", 
      "office": "2107 Rayburn House Office Building", 
      "party": "Democrat", 
      "phone": "202-225-4671", 
      "rss_url": "http://pallone.house.gov/rss.xml", 
      "start": "2019-01-03", 
      "state": "NJ", 
      "type": "rep", 
      "url": "https://pallone.house.gov"
    }, 
    {
      "address": "2107 Rayburn House Office Building Washington DC 20515-3006", 
      "district": 6, 
      "end": "2023-01-03", 
      "office": "2107 Rayburn House Office Building", 
      "party": "Democrat", 
      "phone": "202-225-4671", 
      "rss_url": "http://pallone.house.gov/rss.xml", 
      "start": "2021-01-03", 
      "state": "NJ", 
      "type": "rep", 
      "url": "https://pallone.house.gov"
    }
  ], 
  "url_slug": "nj-frank-pallone"
}