{
  "bio": {
    "birthday": "1962-04-18", 
    "gender": "F"
  }, 
  "id": {
    "aclu_id": "aclu/elections-api/congress_legislator:1044", 
    "ballotpedia": "Karen Handel", 
    "bioguide": "H001078", 
    "cspan": 1026745, 
    "fec": [
      "H8GA06286"
    ], 
    "google_entity_id": "kg:/m/0g838b", 
    "govtrack": 412737, 
    "house_history": 15032448993, 
    "maplight": 2249, 
    "opensecrets": "N00035477", 
    "votesmart": 69553, 
    "wikidata": "Q6369678", 
    "wikipedia": "Karen Handel"
  }, 
  "name": {
    "first": "Karen", 
    "last": "Handel", 
    "official_full": "Karen C. Handel"
  }, 
  "terms": [
    {
      "address": "1211 Longworth House Office Building; Washington DC 20515-1006", 
      "district": 6, 
      "end": "2019-01-03", 
      "fax": null, 
      "office": "1211 Longworth House Office Building", 
      "party": "Republican", 
      "phone": "202-225-4501", 
      "start": "2017-06-26", 
      "state": "GA", 
      "type": "rep", 
      "url": "https://handel.house.gov"
    }
  ], 
  "url_slug": "ga-karen-handel"
}